{"child_modules": ["einsteinpy.metric.schwarzschild", "einsteinpy.metric.robertson-walker-flat"], "data_mtime": 1549480978, "dep_lines": [1, 1], "dep_prios": [5, 5], "dependencies": ["einsteinpy.metric.schwarzschild", "builtins"], "deps_mtime": null, "hash": "b66c33a65c3a429b686e7c0bf3f0c645", "id": "einsteinpy.metric", "ignore_all": false, "interface_hash": "527149789a0f692beaecf22b53eba9f1", "mtime": 1549386489, "options": {"allow_untyped_globals": false, "always_false": [], "always_true": [], "bazel": false, "check_untyped_defs": true, "disallow_any_decorated": false, "disallow_any_explicit": false, "disallow_any_expr": false, "disallow_any_generics": false, "disallow_any_unimported": false, "disallow_incomplete_defs": false, "disallow_subclassing_any": false, "disallow_untyped_calls": false, "disallow_untyped_decorators": false, "disallow_untyped_defs": false, "follow_imports": "normal", "follow_imports_for_stubs": false, "ignore_errors": false, "ignore_missing_imports": true, "local_partial_types": false, "mypyc": false, "no_implicit_optional": false, "platform": "linux", "plugins": [], "show_none_errors": true, "strict_optional": false, "strict_optional_whitelist": null, "warn_no_return": true, "warn_return_any": false, "warn_unused_ignores": false}, "path": "/home/shreyas/Local Forks/einsteinpy/src/einsteinpy/metric/__init__.py", "size": 41, "suppressed": [], "version_id": "0.660"}